pywinmemscanner/__init__.py
pywinmemscanner/__pycache__/__init__.cpython-312.pyc
pywinmemscanner/errors/errors.py
pywinmemscanner/source/src.py
pywinmemscanner/utils/backend/MemoryScanner.dll
pywinmemscanner/utils/backend/__pycache__/memory_extract.cpython-312.pyc
pywinmemscanner/utils/backend/dist/memory_extract.py
pywinmemscanner-0.1.6.dist-info/LICENSE
pywinmemscanner-0.1.6.dist-info/METADATA
pywinmemscanner-0.1.6.dist-info/WHEEL
pywinmemscanner-0.1.6.dist-info/top_level.txt
pywinmemscanner-0.1.6.dist-info/RECORD
