Metadata-Version: 2.1
Name: pywinmemscanner
Version: 0.1.6
Summary: A library for scanning memory of other processes
Home-page: https://github.com/Srinath-N-Gudi/pywinmemscanner
Author: Srinath Gudi
Author-email: srinathngudi11@gmail.com
Keywords: python,library,pywinmemscanner,memory,scanner,memory scanner
Classifier: Programming Language :: Python :: 3
Classifier: License :: OSI Approved :: MIT License
Classifier: Operating System :: Microsoft :: Windows
Requires-Python: >=3.6
License-File: LICENSE
